scipr/__init__.py
scipr/matching.py
scipr/scipr.py
scipr/transform/__init__.py
scipr/transform/affine.py
scipr/transform/autoencoder.py
scipr/transform/base.py
scipr/transform/rigid.py
scipr-0.2.1.dist-info/AUTHORS.rst
scipr-0.2.1.dist-info/LICENSE
scipr-0.2.1.dist-info/METADATA
scipr-0.2.1.dist-info/WHEEL
scipr-0.2.1.dist-info/top_level.txt
scipr-0.2.1.dist-info/RECORD
