Metadata-Version: 2.1
Name: scipr
Version: 0.2.1
Summary: Single Cell Iterative Point set Registration (SCIPR)
Home-page: https://github.com/amiralavi/scipr
Author: Amir Alavi
Author-email: amiralavi@cmu.edu
License: BSD license
Keywords: scipr
Platform: UNKNOWN
Classifier: Development Status :: 2 - Pre-Alpha
Classifier: Intended Audience :: Developers
Classifier: License :: OSI Approved :: BSD License
Classifier: Natural Language :: English
Classifier: Programming Language :: Python :: 3
Classifier: Programming Language :: Python :: 3.6
Classifier: Programming Language :: Python :: 3.7
Classifier: Programming Language :: Python :: 3.8
Requires-Python: >=3.6
Requires-Dist: scikit-learn
Requires-Dist: numpy
Requires-Dist: scipy
Requires-Dist: torch (>=1.2)
Provides-Extra: tensorboard
Requires-Dist: tensorboard (>=1.14) ; extra == 'tensorboard'
Provides-Extra: test
Requires-Dist: anndata ; extra == 'test'
